telegram_bot/__init__.py
telegram_bot/bot.py
telegram_bot/logger.py
telegram_bot/main.py
telegram_bot/validate.py
neojelll_url_shortener_telegram_bot-0.2.21.dist-info/METADATA
neojelll_url_shortener_telegram_bot-0.2.21.dist-info/WHEEL
neojelll_url_shortener_telegram_bot-0.2.21.dist-info/entry_points.txt
neojelll_url_shortener_telegram_bot-0.2.21.dist-info/RECORD
